banklewan09/__init__.py
banklewan09/cylinder.py
banklewan09-0.1.7.dist-info/METADATA
banklewan09-0.1.7.dist-info/WHEEL
banklewan09-0.1.7.dist-info/top_level.txt
banklewan09-0.1.7.dist-info/RECORD
