Metadata-Version: 2.4
Name: banklewan09
Version: 0.1.7
Summary: This is my first package. This package are calculation volume ,lateral and surface in cylinder .
Home-page: https://github.com/yourusername/mypackage
Author: Lewan
Author-email: natthapong.nn@mail.wu.ac.th
Requires-Python: >=3.7
Dynamic: author
Dynamic: author-email
Dynamic: description
Dynamic: description-content-type
Dynamic: home-page
Dynamic: requires-python
Dynamic: summary
